_cephes4py.abi3.so
cephes4py/_test.py
cephes4py/build_hcephes.py
cephes4py/interface.h
cephes4py/__init__.py
cephes4py-0.0.3.dist-info/top_level.txt
cephes4py-0.0.3.dist-info/WHEEL
cephes4py-0.0.3.dist-info/RECORD
cephes4py-0.0.3.dist-info/METADATA
cephes4py-0.0.3.dist-info/LICENSE
cephes4py.libs/libhcephes-ae6048d5.so.0.4.1
