Metadata-Version: 2.1
Name: cephes4py
Version: 0.0.3
Summary: Numba-friendly Python bindings to Cephes math library
Home-page: https://github.com/jonmest/cephes4py
Download-URL: https://github.com/limix/ncephes
Author: Jon Cavallie Mester
Author-email: jonmester3@gmail.com
Maintainer: Jon Cavallie Mester
Maintainer-email: jonmester3@gmail.com
License: MIT
Keywords: cephes,netlib,math,numba,jit
Platform: Windows
Platform: MacOS
Platform: Linux
Classifier: Development Status :: 1 - Planning
Classifier: Environment :: Console
Classifier: License :: OSI Approved :: MIT License
Classifier: Operating System :: OS Independent
Classifier: Programming Language :: Python
License-File: LICENSE
Requires-Dist: cffi (>=1.15.0)
